{
  "sections": {
    "gl_section_brands": {
      "type": "gl_section_brands",
      "blocks": {
        "e04ecef9-dd3f-4b90-8f59-a7482f26302b": {
          "type": "logo_image",
          "settings": {
            "image": "shopify:\/\/shop_images\/blush-by-alexia-designs-5620-vibrant-off-shoulder-sleek-a-line-gown-special-occasion-dress-0-valentine-hot-pink-6565384421433.jpg",
            "link": "shopify:\/\/collections\/blush-sale",
            "title": "Blush by Alexia Designs Prom Dresses"
          }
        },
        "625ecfd3-d744-44c2-8eb5-74fc5775ee06": {
          "type": "logo_image",
          "settings": {
            "link": "",
            "title": ""
          }
        },
        "5a006037-3d2f-49e0-ae85-f314fb2dcfe4": {
          "type": "logo_image",
          "settings": {
            "link": "",
            "title": ""
          }
        },
        "367d2e01-41b8-4ccb-a8c5-7bf87bc8c666": {
          "type": "logo_image",
          "settings": {
            "image": "shopify:\/\/shop_images\/christina-wu-elegance-17906-sleeveless-ribbon-ornate-jersey-gown-special-occasion-dress-0-navy-28497445355603_540x_7bfc7aff-9348-444d-bf92-f105ec7d40f8.webp",
            "link": "",
            "title": ""
          }
        },
        "74d4b674-ee54-4bbf-928f-4f33331fb823": {
          "type": "logo_image",
          "settings": {
            "link": "",
            "title": ""
          }
        },
        "5b4a4fac-addb-4984-b963-35eaca0f4538": {
          "type": "logo_image",
          "settings": {
            "link": "",
            "title": ""
          }
        },
        "ac55c8b0-6202-4d1f-b079-53ca64775bba": {
          "type": "logo_image",
          "settings": {
            "link": "",
            "title": ""
          }
        },
        "82171dcc-8954-468a-ae50-1992bd15f54c": {
          "type": "logo_image",
          "settings": {
            "link": "",
            "title": ""
          }
        },
        "19af4b79-e665-4895-8053-0c68c6c4f824": {
          "type": "logo_image",
          "settings": {
            "link": "",
            "title": ""
          }
        }
      },
      "block_order": [
        "e04ecef9-dd3f-4b90-8f59-a7482f26302b",
        "625ecfd3-d744-44c2-8eb5-74fc5775ee06",
        "5a006037-3d2f-49e0-ae85-f314fb2dcfe4",
        "367d2e01-41b8-4ccb-a8c5-7bf87bc8c666",
        "74d4b674-ee54-4bbf-928f-4f33331fb823",
        "5b4a4fac-addb-4984-b963-35eaca0f4538",
        "ac55c8b0-6202-4d1f-b079-53ca64775bba",
        "82171dcc-8954-468a-ae50-1992bd15f54c",
        "19af4b79-e665-4895-8053-0c68c6c4f824"
      ],
      "settings": {
        "title": "OUR PARTNERS",
        "padding_title": "78px-30px",
        "row_stretch": "default",
        "content_position": "default",
        "use_photowipe": false,
        "view": "grid",
        "space": "20",
        "columns": "4",
        "silder_speed": "5000",
        "silder_per_view": "4",
        "hide_pagination": false,
        "hide_button": false,
        "slider_loop": false,
        "autoplay": false,
        "hide_medium": false,
        "hide_small": false,
        "hide_extra_small": false,
        "section_bg_color": "",
        "section_border_color": "",
        "section_border_style": "solid",
        "section_border": "",
        "section_margin_top": "",
        "section_margin_bottom": "",
        "section_padding_top": "",
        "section_padding_right": "",
        "section_padding_bottom": "",
        "section_padding_left": ""
      }
    },
    "1664516660e078a184": {
      "type": "gl_section_brands",
      "blocks": {
        "16645166600d15f61b-0": {
          "type": "logo_image",
          "settings": {
            "link": "",
            "title": ""
          }
        },
        "16645166600d15f61b-1": {
          "type": "logo_image",
          "settings": {
            "link": "",
            "title": ""
          }
        },
        "16645166600d15f61b-2": {
          "type": "logo_image",
          "settings": {
            "link": "",
            "title": ""
          }
        },
        "16645166600d15f61b-3": {
          "type": "logo_image",
          "settings": {
            "link": "",
            "title": ""
          }
        }
      },
      "block_order": [
        "16645166600d15f61b-0",
        "16645166600d15f61b-1",
        "16645166600d15f61b-2",
        "16645166600d15f61b-3"
      ],
      "settings": {
        "title": "",
        "padding_title": "78px-30px",
        "row_stretch": "default",
        "content_position": "default",
        "use_photowipe": false,
        "view": "grid",
        "space": "20",
        "columns": "4",
        "silder_speed": "5000",
        "silder_per_view": "4",
        "hide_pagination": false,
        "hide_button": false,
        "slider_loop": false,
        "autoplay": false,
        "hide_medium": false,
        "hide_small": false,
        "hide_extra_small": false,
        "section_bg_color": "",
        "section_border_color": "",
        "section_border_style": "solid",
        "section_border": "",
        "section_margin_top": "",
        "section_margin_bottom": "",
        "section_padding_top": "",
        "section_padding_right": "",
        "section_padding_bottom": "",
        "section_padding_left": ""
      }
    }
  },
  "order": [
    "gl_section_brands",
    "1664516660e078a184"
  ]
}
